MANIFEST.in
README.rst
setup.cfg
setup.py
./azkaban_utils/azkaban_util.py
./azkaban_utils/job.py
./azkaban_utils/jobs_checker.py
./azkaban_utils/project.py
./azkaban_utils/project_deployer.py
Azkaban_Utils.egg-info/PKG-INFO
Azkaban_Utils.egg-info/SOURCES.txt
Azkaban_Utils.egg-info/dependency_links.txt
Azkaban_Utils.egg-info/entry_points.txt
Azkaban_Utils.egg-info/top_level.txt